petit/__init__.py
petit/util.py
petit-0.1.0.dist-info/LICENSE
petit-0.1.0.dist-info/METADATA
petit-0.1.0.dist-info/WHEEL
petit-0.1.0.dist-info/top_level.txt
petit-0.1.0.dist-info/RECORD
