Metadata-Version: 2.1
Name: petit
Version: 0.1.0
Summary: protein engineering toolkit
Home-page: https://github.com/kyo46n/petit/
Author: Kyoshiro Nonaka
Author-email: kyo46n@gmail.com
License: MIT
Platform: UNKNOWN
Classifier: Topic :: Scientific/Engineering :: Bio-Informatics
Requires-Dist: numpy
Requires-Dist: pandas
Requires-Dist: scikit-learn
Requires-Dist: scipy
Requires-Dist: biopython
Requires-Dist: xlrd
